django_rest_framework_dango/__init__.py
django_rest_framework_dango/middlewares.py
django_rest_framework_dango/mixins.py
django_rest_framework_dango-0.1.5.dist-info/LICENSE
django_rest_framework_dango-0.1.5.dist-info/METADATA
django_rest_framework_dango-0.1.5.dist-info/WHEEL
django_rest_framework_dango-0.1.5.dist-info/RECORD
