Metadata-Version: 2.1
Name: django-rest-framework-dango
Version: 0.1.5
Summary: A set of viewset mixin for the Django REST Framework.
Home-page: https://github.com/yangeok/django-rest-framework-dango
License: MIT
Author: Yangwook Jeong
Author-email: yangwookee@gmail.com
Requires-Python: >=3.11,<4.0
Classifier: License :: OSI Approved :: MIT License
Classifier: Programming Language :: Python :: 3
Classifier: Programming Language :: Python :: 3.11
Classifier: Programming Language :: Python :: 3.12
Classifier: Programming Language :: Python :: 3.13
Requires-Dist: django (>=4.1.5,<5.0.0)
Requires-Dist: djangorestframework (>=3.14.0,<4.0.0)
Requires-Dist: typing-extensions (>=4.12.2,<5.0.0)
Project-URL: Repository, https://github.com/yangeok/django-rest-framework-dango
